nonebot_plugin_mhcodes/__init__.py
nonebot_plugin_mhcodes/utils.py
nonebot_plugin_mhcodes-0.1.1.dist-info/WHEEL
nonebot_plugin_mhcodes-0.1.1.dist-info/METADATA
nonebot_plugin_mhcodes-0.1.1.dist-info/RECORD
