Metadata-Version: 2.3
Name: nonebot-plugin-mhcodes
Version: 0.1.1
Summary: 记录怪物猎人集会码
Author: padoru233
Requires-Dist: nonebot2>=2.2.0,<3.0.0
Requires-Dist: nonebot-plugin-localstore>=0.7.4,<1.0.0
Requires-Dist: nonebot-plugin-apscheduler>=0.5.0,<1.0.0
Requires-Dist: nonebot-adapter-onebot>=2.0.0,<3.0.0
Requires-Python: >=3.10
Project-URL: Homepage, https://github.com/padoru233/nonebot-plugin-mhcodes
Project-URL: Issues, https://github.com/padoru233/nonebot-plugin-mhcodes/issues
Project-URL: Repository, https://github.com/padoru233/nonebot-plugin-mhcodes.git
